py.typed
tycmd.py
tycmd_wrapper-0.2.1.data/scripts/tycmd
tycmd_wrapper-0.2.1.dist-info/METADATA
tycmd_wrapper-0.2.1.dist-info/WHEEL
tycmd_wrapper-0.2.1.dist-info/licenses/LICENSE
tycmd_wrapper-0.2.1.dist-info/RECORD
