Metadata-Version: 2.1
Name: tycmd-wrapper
Version: 0.2.1
Summary: A python wrapper for tycmd
Keywords: tycmd,teensy,firmware
Author-Email: Florian Rau <bimac@users.noreply.github.com>
License: MIT
Project-URL: Homepage, https://github.com/int-brain-lab/tycmd-wrapper/
Project-URL: Documentation, https://int-brain-lab.github.io/tycmd-wrapper/
Project-URL: Repository, https://github.com/int-brain-lab/tycmd-wrapper.git
Project-URL: Issues, https://github.com/int-brain-lab/tycmd-wrapper/issues
Project-URL: Changelog, https://github.com/int-brain-lab/tycmd-wrapper/blob/main/CHANGELOG.md
Requires-Python: >=3.10
